{
  "project_info": {
    "project_number": "320888211353",
    "project_id": "nivikaasperapp",
    "storage_bucket": "nivikaasperapp.appspot.com"
  },
  "client": [
    {
      "client_info": {
        "mobilesdk_app_id": "1:320888211353:android:b596dd48d3a9c597a17508",
        "android_client_info": {
          "package_name": "com.example.nivika_asper"
        }
      },
      "oauth_client": [
        {
          "client_id": "320888211353-cg9trr84be0tf9ubfeu0e9i3qk5921dd.apps.googleusercontent.com",
          "client_type": 1,
          "android_info": {
            "package_name": "com.example.nivika_asper",
            "certificate_hash": "88fa1d57fd0f72fcf9e667c8249654cb87914622"
          }
        },
        {
          "client_id": "320888211353-hr9j6ii82s2ve1hq6maojg37mm94l3um.apps.googleusercontent.com",
          "client_type": 3
        }
      ],
      "api_key": [
        {
          "current_key": "AIzaSyC7dJYySVc29igkA3AybI7hxPFqCJRbnOo"
        }
      ],
      "services": {
        "appinvite_service": {
          "other_platform_oauth_client": [
            {
              "client_id": "320888211353-hr9j6ii82s2ve1hq6maojg37mm94l3um.apps.googleusercontent.com",
              "client_type": 3
            }
          ]
        }
      }
    }
  ],
  "configuration_version": "1"
}